haipproxy2/__init__.py
haipproxy2/_version.py
haipproxy2/exceptions.py
haipproxy2/logger.py
haipproxy2/client/__init__.py
haipproxy2/client/core.py
haipproxy2/client/py_cli.py
haipproxy2/client/scrapy_middleware.py
haipproxy2/client/squid.py
haipproxy2/config/__init__.py
haipproxy2/config/rules.py
haipproxy2/config/settings.py
haipproxy2/utils/__init__.py
haipproxy2/utils/err_trace.py
haipproxy2/utils/functools.py
haipproxy2/utils/redis_util.py
haipproxy2-0.1.4.dist-info/METADATA
haipproxy2-0.1.4.dist-info/WHEEL
haipproxy2-0.1.4.dist-info/top_level.txt
haipproxy2-0.1.4.dist-info/RECORD
